delighted/__init__.py
delighted/client.py
delighted/errors.py
delighted/http_adapter.py
delighted/http_response.py
delighted/resource.py
delighted/util.py
delighted-1.1.0.dist-info/DESCRIPTION.rst
delighted-1.1.0.dist-info/METADATA
delighted-1.1.0.dist-info/RECORD
delighted-1.1.0.dist-info/WHEEL
delighted-1.1.0.dist-info/metadata.json
delighted-1.1.0.dist-info/pbr.json
delighted-1.1.0.dist-info/top_level.txt
